myhelper/__init__.py
myhelper/cli.py
myhelper/pdftk.py
myhelper/utils.py
myhelper/yt_dlp_helper.py
myhelper-0.1.6a0.dist-info/LICENSE
myhelper-0.1.6a0.dist-info/METADATA
myhelper-0.1.6a0.dist-info/WHEEL
myhelper-0.1.6a0.dist-info/entry_points.txt
myhelper-0.1.6a0.dist-info/top_level.txt
myhelper-0.1.6a0.dist-info/RECORD
