Metadata-Version: 2.1
Name: myhelper
Version: 0.1.6a0
Summary: Code Snippets that I regularly use.
Author-email: Prince Kumar <prince736804545@gmail.com>
Maintainer-email: Prince Kumar <prince736804545@gmail.com>
License: UNLICENSE
Project-URL: Homepage, https://github.com/pk-628996/myhelper
Project-URL: Documentation, https://github.com/pk-628996/myhelper/wiki
Project-URL: Issue Tracker, https://github.com/pk-628996/myhelper/issues
Project-URL: Source Code, https://github.com/pk-628996/myhelper
Project-URL: Changelog, https://github.com/pk-628996/pk-628996/blob/master/CHANGELOG.md
Keywords: myhelper,yt-dlp helper,mypackage
Classifier: Development Status :: 3 - Alpha
Classifier: Intended Audience :: Developers
Classifier: Programming Language :: Python :: 3
Classifier: Programming Language :: Python :: 3.6
Classifier: Programming Language :: Python :: 3.7
Classifier: Programming Language :: Python :: 3.8
Classifier: Programming Language :: Python :: 3.9
Classifier: Programming Language :: Python :: 3.10
Classifier: Programming Language :: Python :: 3.11
Classifier: Programming Language :: Python :: 3.12
Classifier: Programming Language :: Python :: Implementation :: CPython
Classifier: Topic :: Software Development :: Libraries :: Python Modules
Classifier: Operating System :: OS Independent
Requires-Python: >=3.6
License-File: LICENSE
Requires-Dist: aiohttp
Requires-Dist: yt-dlp
Provides-Extra: dev
